{
 "custom_fields": [],
 "custom_perms": [],
 "doctype": "Purchase Invoice",
 "property_setters": [
  {
   "_assign": null,
   "_comments": null,
   "_liked_by": null,
   "_user_tags": null,
   "creation": "2022-02-16 10:01:59.027009",
   "default_value": null,
   "doc_type": "Purchase Invoice",
   "docstatus": 0,
   "doctype_or_field": "DocType",
   "field_name": null,
   "idx": 0,
   "modified": "2022-02-16 10:01:59.027009",
   "modified_by": "Administrator",
   "name": "Purchase Invoice-main-default_print_format",
   "owner": "Administrator",
   "parent": null,
   "parentfield": null,
   "parenttype": null,
   "property": "default_print_format",
   "property_type": "Data",
   "row_name": null,
   "value": "Ngaa Purchase Invoice"
  },
  {
   "_assign": null,
   "_comments": null,
   "_liked_by": null,
   "_user_tags": null,
   "creation": "2022-02-03 14:53:01.495582",
   "default_value": null,
   "doc_type": "Purchase Invoice",
   "docstatus": 0,
   "doctype_or_field": "DocField",
   "field_name": "scan_barcode",
   "idx": 0,
   "modified": "2022-02-03 14:53:01.495582",
   "modified_by": "Administrator",
   "name": "Purchase Invoice-scan_barcode-hidden",
   "owner": "Administrator",
   "parent": null,
   "parentfield": null,
   "parenttype": null,
   "property": "hidden",
   "property_type": "Check",
   "row_name": null,
   "value": "0"
  },
  {
   "_assign": null,
   "_comments": null,
   "_liked_by": null,
   "_user_tags": null,
   "creation": "2021-11-11 23:21:09.411165",
   "default_value": null,
   "doc_type": "Purchase Invoice",
   "docstatus": 0,
   "doctype_or_field": "DocField",
   "field_name": "in_words",
   "idx": 0,
   "modified": "2021-11-11 23:21:09.411165",
   "modified_by": "hillary@commquest.co.za",
   "name": "Purchase Invoice-in_words-print_hide",
   "owner": "hillary@commquest.co.za",
   "parent": null,
   "parentfield": null,
   "parenttype": null,
   "property": "print_hide",
   "property_type": "Check",
   "row_name": null,
   "value": "1"
  },
  {
   "_assign": null,
   "_comments": null,
   "_liked_by": null,
   "_user_tags": null,
   "creation": "2021-11-11 23:21:09.391512",
   "default_value": null,
   "doc_type": "Purchase Invoice",
   "docstatus": 0,
   "doctype_or_field": "DocField",
   "field_name": "in_words",
   "idx": 0,
   "modified": "2021-11-11 23:21:09.391512",
   "modified_by": "hillary@commquest.co.za",
   "name": "Purchase Invoice-in_words-hidden",
   "owner": "hillary@commquest.co.za",
   "parent": null,
   "parentfield": null,
   "parenttype": null,
   "property": "hidden",
   "property_type": "Check",
   "row_name": null,
   "value": "1"
  },
  {
   "_assign": null,
   "_comments": null,
   "_liked_by": null,
   "_user_tags": null,
   "creation": "2021-11-11 23:21:08.887975",
   "default_value": null,
   "doc_type": "Purchase Invoice",
   "docstatus": 0,
   "doctype_or_field": "DocField",
   "field_name": "disable_rounded_total",
   "idx": 0,
   "modified": "2021-11-11 23:21:08.887975",
   "modified_by": "hillary@commquest.co.za",
   "name": "Purchase Invoice-disable_rounded_total-default",
   "owner": "hillary@commquest.co.za",
   "parent": null,
   "parentfield": null,
   "parenttype": null,
   "property": "default",
   "property_type": "Text",
   "row_name": null,
   "value": "1"
  },
  {
   "_assign": null,
   "_comments": null,
   "_liked_by": null,
   "_user_tags": null,
   "creation": "2021-11-11 23:21:08.867278",
   "default_value": null,
   "doc_type": "Purchase Invoice",
   "docstatus": 0,
   "doctype_or_field": "DocField",
   "field_name": "rounded_total",
   "idx": 0,
   "modified": "2021-11-11 23:21:08.867278",
   "modified_by": "hillary@commquest.co.za",
   "name": "Purchase Invoice-rounded_total-print_hide",
   "owner": "hillary@commquest.co.za",
   "parent": null,
   "parentfield": null,
   "parenttype": null,
   "property": "print_hide",
   "property_type": "Check",
   "row_name": null,
   "value": "1"
  },
  {
   "_assign": null,
   "_comments": null,
   "_liked_by": null,
   "_user_tags": null,
   "creation": "2021-11-11 23:21:08.847594",
   "default_value": null,
   "doc_type": "Purchase Invoice",
   "docstatus": 0,
   "doctype_or_field": "DocField",
   "field_name": "rounded_total",
   "idx": 0,
   "modified": "2021-11-11 23:21:08.847594",
   "modified_by": "hillary@commquest.co.za",
   "name": "Purchase Invoice-rounded_total-hidden",
   "owner": "hillary@commquest.co.za",
   "parent": null,
   "parentfield": null,
   "parenttype": null,
   "property": "hidden",
   "property_type": "Check",
   "row_name": null,
   "value": "1"
  },
  {
   "_assign": null,
   "_comments": null,
   "_liked_by": null,
   "_user_tags": null,
   "creation": "2021-11-11 23:21:08.822133",
   "default_value": null,
   "doc_type": "Purchase Invoice",
   "docstatus": 0,
   "doctype_or_field": "DocField",
   "field_name": "base_rounded_total",
   "idx": 0,
   "modified": "2021-11-11 23:21:08.822133",
   "modified_by": "hillary@commquest.co.za",
   "name": "Purchase Invoice-base_rounded_total-print_hide",
   "owner": "hillary@commquest.co.za",
   "parent": null,
   "parentfield": null,
   "parenttype": null,
   "property": "print_hide",
   "property_type": "Check",
   "row_name": null,
   "value": "1"
  },
  {
   "_assign": null,
   "_comments": null,
   "_liked_by": null,
   "_user_tags": null,
   "creation": "2021-11-11 23:21:08.788676",
   "default_value": null,
   "doc_type": "Purchase Invoice",
   "docstatus": 0,
   "doctype_or_field": "DocField",
   "field_name": "base_rounded_total",
   "idx": 0,
   "modified": "2021-11-11 23:21:08.788676",
   "modified_by": "hillary@commquest.co.za",
   "name": "Purchase Invoice-base_rounded_total-hidden",
   "owner": "hillary@commquest.co.za",
   "parent": null,
   "parentfield": null,
   "parenttype": null,
   "property": "hidden",
   "property_type": "Check",
   "row_name": null,
   "value": "1"
  },
  {
   "_assign": null,
   "_comments": null,
   "_liked_by": null,
   "_user_tags": null,
   "creation": "2021-10-29 18:32:28.783452",
   "default_value": null,
   "doc_type": "Purchase Invoice",
   "docstatus": 0,
   "doctype_or_field": "DocField",
   "field_name": "additional_discount_account",
   "idx": 0,
   "modified": "2021-10-29 18:32:28.783452",
   "modified_by": "Administrator",
   "name": "Purchase Invoice-additional_discount_account-mandatory_depends_on",
   "owner": "Administrator",
   "parent": null,
   "parentfield": null,
   "parenttype": null,
   "property": "mandatory_depends_on",
   "property_type": "Code",
   "row_name": null,
   "value": ""
  },
  {
   "_assign": null,
   "_comments": null,
   "_liked_by": null,
   "_user_tags": null,
   "creation": "2021-10-29 18:32:28.765801",
   "default_value": null,
   "doc_type": "Purchase Invoice",
   "docstatus": 0,
   "doctype_or_field": "DocField",
   "field_name": "additional_discount_account",
   "idx": 0,
   "modified": "2021-10-29 18:32:28.765801",
   "modified_by": "Administrator",
   "name": "Purchase Invoice-additional_discount_account-hidden",
   "owner": "Administrator",
   "parent": null,
   "parentfield": null,
   "parenttype": null,
   "property": "hidden",
   "property_type": "Check",
   "row_name": null,
   "value": "1"
  },
  {
   "_assign": null,
   "_comments": null,
   "_liked_by": null,
   "_user_tags": null,
   "creation": "2021-10-29 18:32:28.634286",
   "default_value": null,
   "doc_type": "Purchase Invoice",
   "docstatus": 0,
   "doctype_or_field": "DocField",
   "field_name": "payment_schedule",
   "idx": 0,
   "modified": "2021-10-29 18:32:28.634286",
   "modified_by": "Administrator",
   "name": "Purchase Invoice-payment_schedule-print_hide",
   "owner": "Administrator",
   "parent": null,
   "parentfield": null,
   "parenttype": null,
   "property": "print_hide",
   "property_type": "Check",
   "row_name": null,
   "value": "1"
  },
  {
   "_assign": null,
   "_comments": null,
   "_liked_by": null,
   "_user_tags": null,
   "creation": "2021-10-29 18:32:28.616925",
   "default_value": null,
   "doc_type": "Purchase Invoice",
   "docstatus": 0,
   "doctype_or_field": "DocField",
   "field_name": "due_date",
   "idx": 0,
   "modified": "2021-10-29 18:32:28.616925",
   "modified_by": "Administrator",
   "name": "Purchase Invoice-due_date-print_hide",
   "owner": "Administrator",
   "parent": null,
   "parentfield": null,
   "parenttype": null,
   "property": "print_hide",
   "property_type": "Check",
   "row_name": null,
   "value": "0"
  }
 ],
 "sync_on_migrate": 1
}